datasheets/__init__.py
datasheets/client.py
datasheets/convenience.py
datasheets/exceptions.py
datasheets/helpers.py
datasheets/tab.py
datasheets/workbook.py
datasheets-0.3.0.dist-info/LICENSE.txt
datasheets-0.3.0.dist-info/METADATA
datasheets-0.3.0.dist-info/RECORD
datasheets-0.3.0.dist-info/WHEEL
datasheets-0.3.0.dist-info/top_level.txt
