Metadata-Version: 2.1
Name: datasheets
Version: 0.3.0
Summary: Read data from, write data to, and format Google Sheets from Python
Home-page: https://github.com/Squarespace/datasheets
Author: Squarespace Data Engineering
Author-email: UNKNOWN
License: Apache License 2.0
Download-URL: https://github.com/Squarespace/datasheets/tarball/0.3.0
Platform: UNKNOWN
Classifier: Programming Language :: Python
Classifier: Programming Language :: Python :: 2
Classifier: Programming Language :: Python :: 3
Classifier: Programming Language :: Python :: 2.7
Classifier: Programming Language :: Python :: 3.6
Requires-Dist: google-auth
Requires-Dist: google-auth-oauthlib
Requires-Dist: pandas
Requires-Dist: numpy
Requires-Dist: google-api-python-client (>=1.5.4)
Requires-Dist: six (>=1.10.0)
Requires-Dist: httplib2 (!=0.10.2)
